{
  "SdetBootcampDay1.dll": {
    "C:\\Users\\Steve.Allison\\.nuget\\packages\\microsoft.net.test.sdk\\17.11.0\\build\\netcoreapp3.1\\Microsoft.NET.Test.Sdk.Program.cs": {
      "AutoGeneratedProgram": {
        "System.Void AutoGeneratedProgram::Main(System.String[])": {
          "Lines": {
            "4": 0
          },
          "Branches": []
        }
      }
    },
    "E:\\sdet-bootcamp\\sdet-bootcamp-main\\csharp\\SdetBootcampDay1\\TestObjects\\Account.cs": {
      "SdetBootcampDay1.TestObjects.Account": {
        "SdetBootcampDay1.TestObjects.AccountType SdetBootcampDay1.TestObjects.Account::get_AccountType()": {
          "Lines": {
            "5": 0
          },
          "Branches": []
        },
        "System.Int32 SdetBootcampDay1.TestObjects.Account::get_Balance()": {
          "Lines": {
            "6": 0
          },
          "Branches": []
        },
        "System.Void SdetBootcampDay1.TestObjects.Account::Deposit(System.Int32)": {
          "Lines": {
            "15": 0,
            "16": 0,
            "17": 0
          },
          "Branches": []
        },
        "System.Void SdetBootcampDay1.TestObjects.Account::Withdraw(System.Int32)": {
          "Lines": {
            "20": 0,
            "21": 0,
            "22": 0,
            "23": 0,
            "26": 0,
            "27": 0
          },
          "Branches": [
            {
              "Line": 21,
              "Offset": 27,
              "EndOffset": 29,
              "Path": 0,
              "Ordinal": 0,
              "Hits": 0
            },
            {
              "Line": 21,
              "Offset": 27,
              "EndOffset": 40,
              "Path": 1,
              "Ordinal": 1,
              "Hits": 0
            },
            {
              "Line": 21,
              "Offset": 43,
              "EndOffset": 45,
              "Path": 0,
              "Ordinal": 2,
              "Hits": 0
            },
            {
              "Line": 21,
              "Offset": 43,
              "EndOffset": 57,
              "Path": 1,
              "Ordinal": 3,
              "Hits": 0
            }
          ]
        },
        "System.Void SdetBootcampDay1.TestObjects.Account::.ctor(SdetBootcampDay1.TestObjects.AccountType)": {
          "Lines": {
            "8": 0,
            "9": 0,
            "10": 0,
            "11": 0,
            "12": 0
          },
          "Branches": []
        }
      }
    },
    "E:\\sdet-bootcamp\\sdet-bootcamp-main\\csharp\\SdetBootcampDay1\\TestObjects\\Calculator.cs": {
      "SdetBootcampDay1.TestObjects.Calculator": {
        "System.Int32 SdetBootcampDay1.TestObjects.Calculator::get_Total()": {
          "Lines": {
            "5": 0
          },
          "Branches": []
        },
        "System.Void SdetBootcampDay1.TestObjects.Calculator::Add(System.Int32)": {
          "Lines": {
            "13": 0,
            "14": 0,
            "15": 0
          },
          "Branches": []
        },
        "System.Void SdetBootcampDay1.TestObjects.Calculator::Subtract(System.Int32)": {
          "Lines": {
            "18": 0,
            "19": 0,
            "20": 0
          },
          "Branches": []
        },
        "System.Void SdetBootcampDay1.TestObjects.Calculator::Multiply(System.Int32)": {
          "Lines": {
            "23": 0,
            "24": 0,
            "25": 0
          },
          "Branches": []
        },
        "System.Void SdetBootcampDay1.TestObjects.Calculator::Divide(System.Int32)": {
          "Lines": {
            "28": 0,
            "29": 0,
            "30": 0
          },
          "Branches": []
        },
        "System.Void SdetBootcampDay1.TestObjects.Calculator::.ctor()": {
          "Lines": {
            "7": 0,
            "8": 0,
            "9": 0,
            "10": 0
          },
          "Branches": []
        }
      }
    },
    "E:\\sdet-bootcamp\\sdet-bootcamp-main\\csharp\\SdetBootcampDay1\\TestObjects\\OrderHandler.cs": {
      "SdetBootcampDay1.TestObjects.OrderHandler": {
        "System.Boolean SdetBootcampDay1.TestObjects.OrderHandler::OrderAndPay(SdetBootcampDay1.TestObjects.OrderItem,System.Int32)": {
          "Lines": {
            "18": 2,
            "19": 2,
            "20": 0,
            "21": 0,
            "24": 2,
            "25": 1,
            "26": 1,
            "29": 1,
            "31": 1,
            "32": 1
          },
          "Branches": [
            {
              "Line": 19,
              "Offset": 20,
              "EndOffset": 22,
              "Path": 0,
              "Ordinal": 0,
              "Hits": 0
            },
            {
              "Line": 19,
              "Offset": 20,
              "EndOffset": 68,
              "Path": 1,
              "Ordinal": 1,
              "Hits": 2
            },
            {
              "Line": 24,
              "Offset": 85,
              "EndOffset": 87,
              "Path": 0,
              "Ordinal": 2,
              "Hits": 1
            },
            {
              "Line": 24,
              "Offset": 85,
              "EndOffset": 133,
              "Path": 1,
              "Ordinal": 3,
              "Hits": 1
            }
          ]
        },
        "System.Void SdetBootcampDay1.TestObjects.OrderHandler::AddStock(SdetBootcampDay1.TestObjects.OrderItem,System.Int32)": {
          "Lines": {
            "35": 1,
            "36": 1,
            "37": 1,
            "38": 1,
            "41": 0,
            "42": 0
          },
          "Branches": [
            {
              "Line": 36,
              "Offset": 20,
              "EndOffset": 22,
              "Path": 0,
              "Ordinal": 0,
              "Hits": 1
            },
            {
              "Line": 36,
              "Offset": 20,
              "EndOffset": 68,
              "Path": 1,
              "Ordinal": 1,
              "Hits": 0
            }
          ]
        },
        "System.Int32 SdetBootcampDay1.TestObjects.OrderHandler::GetStockFor(SdetBootcampDay1.TestObjects.OrderItem)": {
          "Lines": {
            "45": 2,
            "46": 2,
            "47": 0,
            "48": 0,
            "51": 2,
            "52": 2
          },
          "Branches": [
            {
              "Line": 46,
              "Offset": 20,
              "EndOffset": 22,
              "Path": 0,
              "Ordinal": 0,
              "Hits": 0
            },
            {
              "Line": 46,
              "Offset": 20,
              "EndOffset": 68,
              "Path": 1,
              "Ordinal": 1,
              "Hits": 2
            }
          ]
        },
        "System.Void SdetBootcampDay1.TestObjects.OrderHandler::.ctor()": {
          "Lines": {
            "5": 3,
            "8": 3,
            "9": 3,
            "10": 3,
            "11": 3,
            "12": 3,
            "14": 3,
            "15": 3
          },
          "Branches": []
        }
      }
    },
    "E:\\sdet-bootcamp\\sdet-bootcamp-main\\csharp\\SdetBootcampDay1\\TestObjects\\PaymentProcessor.cs": {
      "SdetBootcampDay1.TestObjects.PaymentProcessor": {
        "System.Boolean SdetBootcampDay1.TestObjects.PaymentProcessor::PayFor(SdetBootcampDay1.TestObjects.OrderItem,System.Int32)": {
          "Lines": {
            "13": 1,
            "15": 1,
            "16": 1,
            "17": 1,
            "21": 0,
            "22": 1
          },
          "Branches": [
            {
              "Line": 15,
              "Offset": 29,
              "EndOffset": 31,
              "Path": 0,
              "Ordinal": 0,
              "Hits": 1
            },
            {
              "Line": 15,
              "Offset": 29,
              "EndOffset": 36,
              "Path": 1,
              "Ordinal": 1,
              "Hits": 0
            }
          ]
        },
        "System.Void SdetBootcampDay1.TestObjects.PaymentProcessor::.ctor(SdetBootcampDay1.TestObjects.PaymentProcessorType)": {
          "Lines": {
            "7": 3,
            "8": 3,
            "9": 3,
            "10": 3
          },
          "Branches": []
        }
      }
    },
    "E:\\sdet-bootcamp\\sdet-bootcamp-main\\csharp\\SdetBootcampDay1\\Exercises\\Exercises01.cs": {
      "SdetBootcampDay1.Exercises.Exercises01": {
        "System.Void SdetBootcampDay1.Exercises.Exercises01::GivenANewCheckingAccount_WhenIDeposit200_ThenBalanceShouldBe200()": {
          "Lines": {
            "11": 0,
            "12": 0,
            "14": 0,
            "19": 0,
            "25": 0,
            "26": 0
          },
          "Branches": []
        },
        "System.Void SdetBootcampDay1.Exercises.Exercises01::GivenANewSavingsAccount_WhenIDeposit200AndWithdraw100_ThenBalanceShouldBe100()": {
          "Lines": {
            "30": 0,
            "34": 0,
            "40": 0,
            "41": 0,
            "48": 0,
            "49": 0
          },
          "Branches": []
        },
        "System.Void SdetBootcampDay1.Exercises.Exercises01::GivenANewCheckingAccount_WhenIDeposit100AndWithdraw200_ThenBalanceShouldBeNegative100()": {
          "Lines": {
            "53": 0,
            "58": 0,
            "61": 0,
            "64": 0,
            "67": 0,
            "69": 0
          },
          "Branches": []
        }
      }
    },
    "E:\\sdet-bootcamp\\sdet-bootcamp-main\\csharp\\SdetBootcampDay1\\Exercises\\Exercises02.cs": {
      "SdetBootcampDay1.Exercises.Exercises02": {
        "System.Void SdetBootcampDay1.Exercises.Exercises02::CreateNewSavingsAccount_Deposit100Withdraw50_BalanceShouldBe50()": {
          "Lines": {
            "16": 0,
            "17": 0,
            "19": 0,
            "20": 0,
            "22": 0,
            "23": 0
          },
          "Branches": []
        },
        "System.Void SdetBootcampDay1.Exercises.Exercises02::CreateNewSavingsAccount_Deposit1000Withdraw1000_BalanceShouldBe0()": {
          "Lines": {
            "27": 0,
            "28": 0,
            "30": 0,
            "31": 0,
            "33": 0,
            "34": 0
          },
          "Branches": []
        },
        "System.Void SdetBootcampDay1.Exercises.Exercises02::CreateNewSavingsAccount_Deposit250Withdraw1_BalanceShouldBe249()": {
          "Lines": {
            "38": 0,
            "39": 0,
            "41": 0,
            "42": 0,
            "44": 0,
            "45": 0
          },
          "Branches": []
        },
        "System.Void SdetBootcampDay1.Exercises.Exercises02::CreateANewSavingsAccount_DepositThenWithdraw_BalanceShouldBe(System.Int32,System.Int32,System.Int32)": {
          "Lines": {
            "52": 0,
            "53": 0,
            "55": 0,
            "56": 0,
            "58": 0,
            "59": 0
          },
          "Branches": []
        }
      }
    },
    "E:\\sdet-bootcamp\\sdet-bootcamp-main\\csharp\\SdetBootcampDay1\\Exercises\\Exercises03.cs": {
      "SdetBootcampDay1.Exercises.Exercises03": {
        "System.Void SdetBootcampDay1.Exercises.Exercises03::TryingToOverdrawOnASavingsAccountThrowsExpectedException()": {
          "Lines": {
            "11": 0,
            "19": 0,
            "21": 0,
            "23": 0,
            "24": 0,
            "25": 0,
            "26": 0,
            "28": 0,
            "29": 0,
            "30": 0
          },
          "Branches": []
        }
      }
    },
    "E:\\sdet-bootcamp\\sdet-bootcamp-main\\csharp\\SdetBootcampDay1\\Exercises\\TakeHomeExercises.cs": {
      "SdetBootcampDay1.Exercises.TakeHomeExercises": {
        "System.Void SdetBootcampDay1.Exercises.TakeHomeExercises::TestFIFAOrder(SdetBootcampDay1.TestObjects.OrderItem,System.Int32,System.Int32)": {
          "Lines": {
            "19": 1,
            "20": 1,
            "22": 1,
            "23": 1,
            "25": 1
          },
          "Branches": []
        },
        "System.Void SdetBootcampDay1.Exercises.TakeHomeExercises::TestFortniteOrder(SdetBootcampDay1.TestObjects.OrderItem,System.Int32,System.Int32)": {
          "Lines": {
            "34": 1,
            "36": 1,
            "38": 1,
            "39": 1,
            "40": 1,
            "41": 1,
            "43": 1,
            "44": 1,
            "45": 1
          },
          "Branches": []
        },
        "System.Void SdetBootcampDay1.Exercises.TakeHomeExercises::TestFortniteOrder(SdetBootcampDay1.TestObjects.OrderItem,System.Int32)": {
          "Lines": {
            "54": 1,
            "56": 1,
            "58": 1,
            "59": 1,
            "60": 1,
            "61": 1,
            "63": 1,
            "64": 1
          },
          "Branches": []
        }
      }
    },
    "E:\\sdet-bootcamp\\sdet-bootcamp-main\\csharp\\SdetBootcampDay1\\Examples\\Examples01.cs": {
      "SdetBootcampDay1.Examples.Examples01": {
        "System.Void SdetBootcampDay1.Examples.Examples01::GivenANewCalculator_WhenIAdd2and2_thenTheTotalIs4()": {
          "Lines": {
            "11": 0,
            "13": 0,
            "16": 0,
            "17": 0,
            "20": 0,
            "21": 0
          },
          "Branches": []
        }
      }
    },
    "E:\\sdet-bootcamp\\sdet-bootcamp-main\\csharp\\SdetBootcampDay1\\Examples\\Examples02.cs": {
      "SdetBootcampDay1.Examples.Examples02": {
        "System.Void SdetBootcampDay1.Examples.Examples02::GivenANewCalculator_WhenIAddTwoNumbers_thenTheTotalIsAsExpected(System.Int32,System.Int32,System.Int32)": {
          "Lines": {
            "14": 0,
            "15": 0,
            "17": 0,
            "18": 0,
            "20": 0,
            "21": 0
          },
          "Branches": []
        },
        "System.Void SdetBootcampDay1.Examples.Examples02::GivenANewCalculator_WhenIAddTwoNumbers_thenTheTotalIsAsExpected_UsingTestCaseSource(System.Int32,System.Int32,System.Int32)": {
          "Lines": {
            "26": 0,
            "27": 0,
            "29": 0,
            "30": 0,
            "32": 0,
            "33": 0
          },
          "Branches": []
        }
      },
      "SdetBootcampDay1.Examples.Examples02/<CalculatorAdditionTestData>d__2": {
        "System.Boolean SdetBootcampDay1.Examples.Examples02/<CalculatorAdditionTestData>d__2::MoveNext()": {
          "Lines": {
            "36": 2,
            "37": 2,
            "38": 2,
            "39": 2,
            "40": 2,
            "41": 2,
            "42": 2,
            "43": 2
          },
          "Branches": []
        }
      }
    },
    "E:\\sdet-bootcamp\\sdet-bootcamp-main\\csharp\\SdetBootcampDay1\\Examples\\Examples03.cs": {
      "SdetBootcampDay1.Examples.Examples03": {
        "System.Void SdetBootcampDay1.Examples.Examples03::CheckThatDividingByZeroThrowsDivideByZeroException()": {
          "Lines": {
            "11": 0,
            "12": 0,
            "14": 0,
            "16": 0,
            "17": 0,
            "18": 0,
            "19": 0,
            "20": 0
          },
          "Branches": []
        },
        "System.Void SdetBootcampDay1.Examples.Examples03::YouCanAlsoVerifyTheExceptionMessage()": {
          "Lines": {
            "24": 0,
            "25": 0,
            "27": 0,
            "29": 0,
            "30": 0,
            "31": 0,
            "32": 0,
            "34": 0,
            "35": 0
          },
          "Branches": []
        },
        "System.Void SdetBootcampDay1.Examples.Examples03::CheckingForADifferentExceptionFailsTheTest()": {
          "Lines": {
            "39": 0,
            "40": 0,
            "42": 0,
            "44": 0,
            "45": 0,
            "46": 0,
            "47": 0,
            "48": 0
          },
          "Branches": []
        }
      }
    },
    "E:\\sdet-bootcamp\\sdet-bootcamp-main\\csharp\\SdetBootcampDay1\\Answers\\Answers01.cs": {
      "SdetBootcampDay1.Answers.Answers01": {
        "System.Void SdetBootcampDay1.Answers.Answers01::GivenANewCheckingAccount_WhenIDeposit200_ThenBalanceShouldBe200()": {
          "Lines": {
            "11": 0,
            "12": 0,
            "14": 0,
            "19": 0,
            "24": 0,
            "25": 0
          },
          "Branches": []
        },
        "System.Void SdetBootcampDay1.Answers.Answers01::GivenANewSavingsAccount_WhenIDeposit200AndWithdraw100_ThenBalanceShouldBe100()": {
          "Lines": {
            "29": 0,
            "33": 0,
            "38": 0,
            "39": 0,
            "44": 0,
            "45": 0
          },
          "Branches": []
        },
        "System.Void SdetBootcampDay1.Answers.Answers01::GivenANewCheckingAccount_WhenIDeposit100AndWithdraw200_ThenBalanceShouldBeMinus100()": {
          "Lines": {
            "56": 0,
            "57": 0,
            "59": 0,
            "60": 0,
            "62": 0,
            "63": 0
          },
          "Branches": []
        }
      }
    },
    "E:\\sdet-bootcamp\\sdet-bootcamp-main\\csharp\\SdetBootcampDay1\\Answers\\Answers02.cs": {
      "SdetBootcampDay1.Answers.Answers02": {
        "System.Void SdetBootcampDay1.Answers.Answers02::SavingsAccount_DepositThenWithdraw_BalanceShouldBeUpdatedAccordingly(System.Int32,System.Int32,System.Int32)": {
          "Lines": {
            "19": 0,
            "20": 0,
            "22": 0,
            "23": 0,
            "25": 0,
            "26": 0
          },
          "Branches": []
        },
        "System.Void SdetBootcampDay1.Answers.Answers02::SavingsAccount_DepositThenWithdraw_BalanceShouldBeUpdatedAccordingly_UsingTestCaseSource(System.Int32,System.Int32,System.Int32)": {
          "Lines": {
            "31": 0,
            "32": 0,
            "34": 0,
            "35": 0,
            "37": 0,
            "39": 0
          },
          "Branches": []
        }
      },
      "SdetBootcampDay1.Answers.Answers02/<WithdrawTestData>d__2": {
        "System.Boolean SdetBootcampDay1.Answers.Answers02/<WithdrawTestData>d__2::MoveNext()": {
          "Lines": {
            "42": 2,
            "43": 2,
            "44": 2,
            "45": 2,
            "46": 2,
            "47": 2,
            "48": 2,
            "49": 2
          },
          "Branches": []
        }
      }
    },
    "E:\\sdet-bootcamp\\sdet-bootcamp-main\\csharp\\SdetBootcampDay1\\Answers\\Answers03.cs": {
      "SdetBootcampDay1.Answers.Answers03": {
        "System.Void SdetBootcampDay1.Answers.Answers03::TryingToOverdrawOnASavingsAccountThrowsExpectedException()": {
          "Lines": {
            "11": 0,
            "19": 0,
            "21": 0,
            "23": 0,
            "24": 0,
            "25": 0,
            "26": 0,
            "28": 0,
            "30": 0,
            "31": 0
          },
          "Branches": []
        }
      }
    },
    "E:\\sdet-bootcamp\\sdet-bootcamp-main\\csharp\\SdetBootcampDay1\\Answers\\TakeHomeAnswers.cs": {
      "SdetBootcampDay1.Answers.TakeHomeAnswers": {
        "System.Void SdetBootcampDay1.Answers.TakeHomeAnswers::Order1CopyOfFIFA24_ShouldLeave9CopiesRemaining()": {
          "Lines": {
            "19": 0,
            "20": 0,
            "22": 0,
            "24": 0,
            "25": 0
          },
          "Branches": []
        },
        "System.Void SdetBootcampDay1.Answers.TakeHomeAnswers::Order101CopiesOfFortnite_ShouldYieldArgumentException()": {
          "Lines": {
            "34": 0,
            "35": 0,
            "37": 0,
            "38": 0,
            "39": 0,
            "40": 0,
            "42": 0,
            "43": 0
          },
          "Branches": []
        },
        "System.Void SdetBootcampDay1.Answers.TakeHomeAnswers::AddStockForDayOfTheTentacle_ShouldYieldArgumentException()": {
          "Lines": {
            "52": 0,
            "53": 0,
            "55": 0,
            "56": 0,
            "57": 0,
            "58": 0,
            "60": 0,
            "61": 0
          },
          "Branches": []
        }
      }
    }
  }
}